LICENSE
MANIFEST.in
README.md
requirements.txt
setup.py
bela/__init__.py
bela/__version__.py
bela/bela1.py
bela/bela2.py
bela/builder.py
bela/common.py
bela/lex.py
bela.egg-info/PKG-INFO
bela.egg-info/SOURCES.txt
bela.egg-info/dependency_links.txt
bela.egg-info/requires.txt
bela.egg-info/top_level.txt
bela/data/__init__.py
bela/data/bela_v3_blank.eaf
bela/data/cmn_lex.txt.gz
bela/data/msa_lex.txt.gz
test/test_bela.py